Metadata-Version: 2.1
Name: pipemake-utils
Version: 1.3.2
Summary: Pipemake Utilities
Home-page: https://github.com/kocherlab/pipemake_utils
License: MIT
Project-URL: Code, https://github.com/kocherlab/pipemake_utils
Project-URL: Issue tracker, https://github.com/kocherlab/pipemake_utils/issues
Requires-Python: >=3.7
License-File: LICENSE
